aqua/__init__.py
aqua/__main__.py
aqua/cli.py
aqua/coordinator.py
aqua/db.py
aqua/models.py
aqua/utils.py
aqua/templates/AGENT_INSTRUCTIONS.md
aqua_coord-0.5.0.dist-info/METADATA
aqua_coord-0.5.0.dist-info/WHEEL
aqua_coord-0.5.0.dist-info/entry_points.txt
aqua_coord-0.5.0.dist-info/licenses/LICENSE
aqua_coord-0.5.0.dist-info/RECORD
