Metadata-Version: 2.4
Name: aqua-coord
Version: 0.5.0
Summary: Autonomous QUorum of Agents - Lightweight coordinator for CLI AI agents
Project-URL: Homepage, https://github.com/vignesh07/aqua
Project-URL: Repository, https://github.com/vignesh07/aqua
Project-URL: Issues, https://github.com/vignesh07/aqua/issues
Author-email: Vignesh <mailvgnsh@gmail.com>
License-Expression: MIT
License-File: LICENSE
Keywords: agents,ai,claude,cli,codex,coordination,gemini,multi-agent
Classifier: Development Status :: 3 - Alpha
Classifier: Environment :: Console
Classifier: Intended Audience :: Developers
Classifier: License :: OSI Approved :: MIT License
Classifier: Operating System :: OS Independent
Classifier: Programming Language :: Python :: 3
Classifier: Programming Language :: Python :: 3.10
Classifier: Programming Language :: Python :: 3.11
Classifier: Programming Language :: Python :: 3.12
Classifier: Topic :: Software Development :: Libraries :: Python Modules
Classifier: Topic :: System :: Distributed Computing
Requires-Python: >=3.10
Requires-Dist: click>=8.0
Requires-Dist: rich>=13.0
Provides-Extra: dev
Requires-Dist: mypy>=1.0; extra == 'dev'
Requires-Dist: pytest-asyncio>=0.21; extra == 'dev'
Requires-Dist: pytest-cov>=4.0; extra == 'dev'
Requires-Dist: pytest>=7.0; extra == 'dev'
Requires-Dist: ruff>=0.1; extra == 'dev'
